{"items": [
{"concept": {"CONCEPT_CODE": "1", "CONCEPT_ID": 19123240}, "isExcluded": false, "includeDescendants": false, "includeMapped": false},
{"concept": {"CONCEPT_CODE": "1", "CONCEPT_ID": 35852880}, "isExcluded": false, "includeDescendants": true, "includeMapped": false},
{"concept": {"CONCEPT_CODE": "1", "CONCEPT_ID": 40053216}, "isExcluded": false, "includeDescendants": true, "includeMapped": false},
{"concept": {"CONCEPT_CODE": "1", "CONCEPT_ID": 43141008}, "isExcluded": false, "includeDescendants": true, "includeMapped": false},
{"concept": {"CONCEPT_CODE": "1", "CONCEPT_ID": 43174216}, "isExcluded": false, "includeDescendants": true, "includeMapped": false},
{"concept": {"CONCEPT_CODE": "1", "CONCEPT_ID": 41173944}, "isExcluded": false, "includeDescendants": true, "includeMapped": false},
{"concept": {"CONCEPT_CODE": "1", "CONCEPT_ID": 43141009}, "isExcluded": false, "includeDescendants": true, "includeMapped": false},
{"concept": {"CONCEPT_CODE": "1", "CONCEPT_ID": 35137663}, "isExcluded": false, "includeDescendants": true, "includeMapped": false},
{"concept": {"CONCEPT_CODE": "1", "CONCEPT_ID": 35852878}, "isExcluded": false, "includeDescendants": true, "includeMapped": false},
{"concept": {"CONCEPT_CODE": "1", "CONCEPT_ID": 40053217}, "isExcluded": false, "includeDescendants": true, "includeMapped": false}
]}
