{"items": [
{"concept": {"CONCEPT_CODE": "1", "CONCEPT_ID": 19078399}, "isExcluded": false, "includeDescendants": false, "includeMapped": false},
{"concept": {"CONCEPT_CODE": "1", "CONCEPT_ID": 43715286}, "isExcluded": false, "includeDescendants": true, "includeMapped": false},
{"concept": {"CONCEPT_CODE": "1", "CONCEPT_ID": 40892726}, "isExcluded": false, "includeDescendants": true, "includeMapped": false},
{"concept": {"CONCEPT_CODE": "1", "CONCEPT_ID": 42478984}, "isExcluded": false, "includeDescendants": true, "includeMapped": false},
{"concept": {"CONCEPT_CODE": "1", "CONCEPT_ID": 42480187}, "isExcluded": false, "includeDescendants": true, "includeMapped": false},
{"concept": {"CONCEPT_CODE": "1", "CONCEPT_ID": 2042246}, "isExcluded": false, "includeDescendants": true, "includeMapped": false},
{"concept": {"CONCEPT_CODE": "1", "CONCEPT_ID": 40091408}, "isExcluded": false, "includeDescendants": true, "includeMapped": false}
]}
